ReForBeginners/README.md
ReForBeginners/__init__.py
ReForBeginners/__main__.py
ReForBeginners/file.epub
ReForBeginners/index.html
ReForBeginners/css/__init__.py
ReForBeginners/css/annotations.css
ReForBeginners/css/main.css
ReForBeginners/css/normalize.css
ReForBeginners/css/popup.css
ReForBeginners/font/__init__.py
ReForBeginners/font/fontello.eot
ReForBeginners/font/fontello.svg
ReForBeginners/font/fontello.ttf
ReForBeginners/font/fontello.woff
ReForBeginners/img/__init__.py
ReForBeginners/img/annotator-glyph-sprite.png
ReForBeginners/img/annotator-icon-sprite.png
ReForBeginners/img/apple-touch-icon.png
ReForBeginners/img/cancelfullscreen.png
ReForBeginners/img/close.png
ReForBeginners/img/fullscreen.png
ReForBeginners/img/loader.gif
ReForBeginners/img/menu-icon.png
ReForBeginners/img/save.png
ReForBeginners/img/saved.png
ReForBeginners/img/settings-s.png
ReForBeginners/img/settings.png
ReForBeginners/img/star.png
ReForBeginners/js/__init__.py
ReForBeginners/js/epub.js
ReForBeginners/js/epub.min.js
ReForBeginners/js/epub.min.map
ReForBeginners/js/hooks.min.js
ReForBeginners/js/hooks.min.map
ReForBeginners/js/reader.js
ReForBeginners/js/reader.js.map
ReForBeginners/js/reader.min.js
ReForBeginners/js/reader.min.map
ReForBeginners/js/hooks/__init__.py
ReForBeginners/js/hooks/extensions/__init__.py
ReForBeginners/js/hooks/extensions/highlight.js
ReForBeginners/js/libs/__init__.py
ReForBeginners/js/libs/jquery.min.js
ReForBeginners/js/libs/localforage.min.js
ReForBeginners/js/libs/screenfull.js
ReForBeginners/js/libs/screenfull.min.js
ReForBeginners/js/libs/zip.min.js
ReForBeginners/js/plugins/__init__.py
ReForBeginners/js/plugins/hypothesis.js
ReForBeginners/js/plugins/search.js
re_for_beginners-2024.3.2.0.dist-info/METADATA
re_for_beginners-2024.3.2.0.dist-info/WHEEL
re_for_beginners-2024.3.2.0.dist-info/entry_points.txt
re_for_beginners-2024.3.2.0.dist-info/top_level.txt
re_for_beginners-2024.3.2.0.dist-info/RECORD
